auralflow/__init__.py
auralflow/datasets/__init__.py
auralflow/datasets/datasets.py
auralflow/losses/__init__.py
auralflow/losses/losses.py
auralflow/models/__init__.py
auralflow/models/architectures.py
auralflow/models/base.py
auralflow/models/generative_model.py
auralflow/models/mask_model.py
auralflow/separate.py
auralflow/train.py
auralflow/trainer/__init__.py
auralflow/trainer/callbacks.py
auralflow/trainer/trainer.py
auralflow/trainer/validator.py
auralflow/utils/__init__.py
auralflow/utils/data_utils.py
auralflow/visualizer/__init__.py
auralflow/visualizer/progress.py
auralflow/visualizer/visualizer.py
auralflow-0.1.0.dist-info/LICENSE
auralflow-0.1.0.dist-info/WHEEL
auralflow-0.1.0.dist-info/METADATA
auralflow-0.1.0.dist-info/RECORD
