Metadata-Version: 2.1
Name: auralflow
Version: 0.1.0
Summary: A lightweight music source separation toolkit.
License: MIT
Author: Kian Zohoury
Author-email: kzohoury@berkeley.edu
Requires-Python: >=3.9,<3.10
Classifier: License :: OSI Approved :: MIT License
Classifier: Programming Language :: Python :: 3
Classifier: Programming Language :: Python :: 3.9
Requires-Dist: fast-bss-eval (>=0.1.3,<0.2.0)
Requires-Dist: jupyter (>=1.0.0,<2.0.0)
Requires-Dist: pendulum (>=2.1.2,<3.0.0)
Requires-Dist: torch (>=1.11.0,<2.0.0)
Requires-Dist: torchaudio (>=0.11.0,<0.12.0)
